QCLSolver/__init__.py
QCLSolver/core.cp38-win_amd64.pyd
QCLSolver/data.py
QCLSolver/solver.py
QCLSolver/tool.py
QCLSolver-1.0.4.dist-info/LICENSE
QCLSolver-1.0.4.dist-info/METADATA
QCLSolver-1.0.4.dist-info/WHEEL
QCLSolver-1.0.4.dist-info/top_level.txt
QCLSolver-1.0.4.dist-info/RECORD
