Metadata-Version: 2.1
Name: QCLSolver
Version: 1.0.4
Summary: A tool for cluster expansion solver.
Home-page: UNKNOWN
Author: Yuexun Huang & Ke Lin
Author-email: yesunhuang@mail.ustc.edu.cn
License: UNKNOWN
Project-URL: Documentation, https://github.com/yesunhuang/QCLS
Project-URL: Source, https://github.com/yesunhuang/QCLS
Project-URL: Tracker, https://github.com/yesunhuang/QCLS/issues
Keywords: physics quantum optics
Platform: UNKNOWN
Classifier: Development Status :: 5 - Production/Stable
Classifier: Intended Audience :: Science/Research
Classifier: Topic :: Scientific/Engineering :: Physics
Classifier: License :: OSI Approved :: GNU General Public License v3 (GPLv3)
Classifier: Natural Language :: English
Classifier: Operating System :: OS Independent
Classifier: Programming Language :: C++
Requires-Python: >=3.7
Requires-Dist: scipy (>=1.4.1)
Requires-Dist: numpy
